[
  {
    "id": "tr_personal_la",
    "name": "Персональный ЛА",
    "category": "Воздушный",
    "description": "Одноместный летательный аппарат для города. Капсула с микроверсией двигателя СВВП. Есть «богатый крюк» №1. Управляется одной рукояткой или через Порт.",
    "sc": 15,
    "seats": 1,
    "sko_mech": 15,
    "sko_narr": "80 км/ч",
    "price": 10000
  },
  {
    "id": "tr_gyrocopter",
    "name": "Гироптер",
    "category": "Воздушный",
    "description": "Двухместный гирокоптер с маленьким винтом позади. Нужна маленькая ВПП. Патрульно-разведывательная машина. Пригоден для длительных перелётов.",
    "sc": 35,
    "seats": 2,
    "sko_mech": 20,
    "sko_narr": "160 км/ч",
    "price": 15000
  },
  {
    "id": "tr_helicopter",
    "name": "Вертолёт",
    "category": "Воздушный",
    "description": "Стандартная винтокрылая машина. С 2035 года отказались от хвостовых винтов в пользу фенестронов или соосной схемы. Позволяет летать между континентами.",
    "sc": 70,
    "seats": 4,
    "sko_mech": 40,
    "sko_narr": "320 км/ч",
    "price": 40000
  },
  {
    "id": "tr_civil_vtol",
    "name": "Гражданский СВВП",
    "category": "Воздушный",
    "description": "Передовые технологии авиации. VIP-фургоны до обычных маршрутов. В ряде стран гражданским запрещено иметь СВВП. Летают экстренные службы, скорая, общественный транспорт.",
    "sc": 100,
    "seats": "4–18",
    "sko_mech": 40,
    "sko_narr": "320 км/ч",
    "price": 90000,
    "price_note": "60 000–120 000 уе (зависит от типа)"
  },
  {
    "id": "tr_combat_vtol",
    "name": "Боевой СВВП",
    "category": "Воздушный",
    "description": "Военизированная десантная версия. Внутри склад с оружием и патронами, на корпусе турели и ракетомёты.",
    "sc": 150,
    "seats": 12,
    "sko_mech": 50,
    "sko_narr": "400 км/ч",
    "price": 100000
  },
  {
    "id": "tr_sport_vtol",
    "name": "Спортивный СВВП",
    "category": "Воздушный",
    "description": "Настоящий гиперкар среди СВВП. Богачи и шейхи летают на таких. Развивает огромную скорость.",
    "sc": 60,
    "seats": 2,
    "sko_mech": 60,
    "sko_narr": "480 км/ч",
    "price": 200000
  },
  {
    "id": "tr_skyliner",
    "name": "Скайлинер",
    "category": "Воздушный",
    "description": "Тяжёлый гибрид самолёта и дирижабля. Используется вольниками для больших партий груза. Может зависать на месте и летать практически бесконечно. Настоящие летучие города.",
    "sc": 200,
    "seats": "2 на каюту",
    "sko_mech": 20,
    "sko_narr": "160 км/ч",
    "price": 10000,
    "price_note": "10 000 уе за каюту, мин. 3 каюты"
  },
  {
    "id": "tr_jet_ski",
    "name": "Гидроцикл",
    "category": "Водный",
    "description": "Самый обычный гидроцикл.",
    "sc": 35,
    "seats": 2,
    "sko_mech": 20,
    "sko_narr": "100 км/ч",
    "price": 20000
  },
  {
    "id": "tr_fishing_boat",
    "name": "Рыбацкий катер",
    "category": "Водный",
    "description": "Медлительный катер для ловли рыбы или перевозки групп туристов по красивым местам.",
    "sc": 50,
    "seats": 6,
    "sko_mech": 8,
    "sko_narr": "40 км/ч",
    "price": 25000
  },
  {
    "id": "tr_speedboat",
    "name": "Скоростной Катер",
    "category": "Водный",
    "description": "Скоростной катер для преодоления больших расстояний по рекам, озёрам и морю. Оснащён закрытой кабиной.",
    "sc": 40,
    "seats": 4,
    "sko_mech": 20,
    "sko_narr": "100 км/ч",
    "price": 30000
  },
  {
    "id": "tr_cruise_yacht",
    "name": "Круизная Яхта",
    "category": "Водный",
    "description": "Роскошная круизная яхта с каютами. Для бледных миллиардеров и служителей церкви, ходящих по водной глади.",
    "sc": 70,
    "seats": "4 на каюту, мин. 2",
    "sko_mech": 15,
    "sko_narr": "75 км/ч",
    "price": 20000,
    "price_note": "20 000 уе за каюту, мин. 2 каюты"
  },
  {
    "id": "tr_barge",
    "name": "Баржа",
    "category": "Водный",
    "description": "Большая, неповоротливая, медлительная баржа для перевозки большого объёма груза или людей. Бывают разных размеров. Морские сухогрузы в эту категорию не входят.",
    "sc": 100,
    "seats": 32,
    "sko_mech": 10,
    "sko_narr": "50 км/ч",
    "price": 100000
  },
  {
    "id": "tr_micromobile",
    "name": "Компактный Микро-мобиль",
    "category": "Наземный",
    "description": "Обычный городской автомобиль для одинокого человека на обычном двигателе.",
    "sc": 50,
    "seats": 1,
    "sko_mech": 20,
    "sko_narr": "160 км/ч",
    "price": 15000
  },
  {
    "id": "tr_car",
    "name": "Обычный Автомобиль",
    "category": "Наземный",
    "description": "Городской автомобиль, универсал или минивэн.",
    "sc": 60,
    "seats": "2 / 4 / 6",
    "sko_mech": 20,
    "sko_narr": "160 км/ч",
    "price": 40000,
    "price_note": "35 000 / 40 000 / 50 000 уе"
  },
  {
    "id": "tr_sportscar",
    "name": "Спорткар",
    "category": "Наземный",
    "description": "Спортивная машина на токо-двигателе. Развивает большую скорость.",
    "sc": 40,
    "seats": 2,
    "sko_mech": 40,
    "sko_narr": "320 км/ч",
    "price": 50000
  },
  {
    "id": "tr_supercar",
    "name": "Суперкар",
    "category": "Наземный",
    "description": "Самые шикарные автомобили. На каждую ось — отдельный токо-двигатель. Разгоняется до сумасшедших скоростей, практически неуправляем. Часто встречаются на Транс-германских автобанах.",
    "sc": 40,
    "seats": 2,
    "sko_mech": 60,
    "sko_narr": "480 км/ч",
    "price": 100000
  },
  {
    "id": "tr_road_bike",
    "name": "Шоссейный байк",
    "category": "Наземный",
    "description": "Обычный байк, чоппер или шоссейный мотолайнер. Пересечь страну и не устать.",
    "sc": 35,
    "seats": 2,
    "sko_mech": 20,
    "sko_narr": "160 км/ч",
    "price": 15000
  },
  {
    "id": "tr_sport_bike",
    "name": "Спортивный байк",
    "category": "Наземный",
    "description": "Спортивный байк с большой скоростью. Приводится токо-двигателем.",
    "sc": 35,
    "seats": 2,
    "sko_mech": 40,
    "sko_narr": "320 км/ч",
    "price": 30000
  },
  {
    "id": "tr_truck_train",
    "name": "Автопоезд",
    "category": "Наземный",
    "description": "Фура с прицеплёнными секциями. Секции могут быть жилые или грузовые либо бронированные. Вольники делают целые дорожные крепости с турелями и гаражами для байков и точек.",
    "sc": 70,
    "seats": "4 на секцию",
    "sko_mech": 20,
    "sko_narr": "160 км/ч",
    "price": 50000,
    "price_note": "50 000 уе за секцию, мин. 4 секции"
  },
  {
    "id": "tr_truck",
    "name": "Фура",
    "category": "Наземный",
    "description": "Любимый транспорт наземных вольников. Фура, большой самосвал и подобные.",
    "sc": 70,
    "seats": 4,
    "sko_mech": 25,
    "sko_narr": "200 км/ч",
    "price": 50000
  },
  {
    "id": "tr_superbike",
    "name": "Супербайк",
    "category": "Наземный",
    "description": "Байк со специальным шлемом через Порт водителя. Сопроцессор в голове водителя реагирует быстрее самого водителя. На каждом колесе отдельный токо-двигатель. При отключении сам останавливается.",
    "sc": 25,
    "seats": 2,
    "sko_mech": 70,
    "sko_narr": "540 км/ч",
    "price": 120000
  }
]
